<?xml version="1.0" encoding="UTF-8"?>
<MetaDataObject xmlns="http://v8.1c.ru/8.3/MDClasses" xmlns:app="http://v8.1c.ru/8.2/managed-application/core" xmlns:cfg="http://v8.1c.ru/8.1/data/enterprise/current-config" xmlns:cmi="http://v8.1c.ru/8.2/managed-application/cmi" xmlns:ent="http://v8.1c.ru/8.1/data/enterprise" xmlns:lf="http://v8.1c.ru/8.2/managed-application/logform" xmlns:style="http://v8.1c.ru/8.1/data/ui/style" xmlns:sys="http://v8.1c.ru/8.1/data/ui/fonts/system" xmlns:v8="http://v8.1c.ru/8.1/data/core" xmlns:v8ui="http://v8.1c.ru/8.1/data/ui" xmlns:web="http://v8.1c.ru/8.1/data/ui/colors/web" xmlns:win="http://v8.1c.ru/8.1/data/ui/colors/windows" xmlns:xen="http://v8.1c.ru/8.3/xcf/enums" xmlns:xpr="http://v8.1c.ru/8.3/xcf/predef" xmlns:xr="http://v8.1c.ru/8.3/xcf/readable" xmlns:xs="http://www.w3.org/2001/XMLSchema" xmlns:xsi="http://www.w3.org/2001/XMLSchema-instance" version="2.3">
	<Constant uuid="505944d6-849e-4b80-8ab3-e97433bb02cb">
		<InternalInfo>
			<xr:GeneratedType name="ConstantManager.verify_email" category="Manager">
				<xr:TypeId>9fc5bba0-5476-4212-ba86-cd06bef22ff3</xr:TypeId>
				<xr:ValueId>e826af47-3a58-4318-8658-af9c30e7c66e</xr:ValueId>
			</xr:GeneratedType>
			<xr:GeneratedType name="ConstantValueManager.verify_email" category="ValueManager">
				<xr:TypeId>90bd5542-ce51-432a-8885-13c3691313f3</xr:TypeId>
				<xr:ValueId>ee33dad9-f07d-4f55-ba5e-518a9a1a5ac4</xr:ValueId>
			</xr:GeneratedType>
		</InternalInfo>
		<Properties>
			<Name>verify_email</Name>
			<Synonym>
				<v8:item>
					<v8:lang>en</v8:lang>
					<v8:content>Verify email</v8:content>
				</v8:item>
			</Synonym>
			<Comment/>
			<Type>
				<v8:Type>xs:boolean</v8:Type>
			</Type>
			<UseStandardCommands>false</UseStandardCommands>
			<DefaultForm/>
			<ExtendedPresentation/>
			<Explanation/>
			<PasswordMode>false</PasswordMode>
			<Format/>
			<EditFormat/>
			<ToolTip/>
			<MarkNegatives>false</MarkNegatives>
			<Mask/>
			<MultiLine>false</MultiLine>
			<ExtendedEdit>false</ExtendedEdit>
			<MinValue xsi:nil="true"/>
			<MaxValue xsi:nil="true"/>
			<FillChecking>DontCheck</FillChecking>
			<ChoiceFoldersAndItems>Items</ChoiceFoldersAndItems>
			<ChoiceParameterLinks/>
			<ChoiceParameters/>
			<QuickChoice>Auto</QuickChoice>
			<ChoiceForm/>
			<LinkByType/>
			<ChoiceHistoryOnInput>Auto</ChoiceHistoryOnInput>
			<DataLockControlMode>Managed</DataLockControlMode>
		</Properties>
	</Constant>
</MetaDataObject>